kivy_weather_app_package/APIK.json
kivy_weather_app_package/__init__.py
kivy_weather_app_package/cloudy.jpg
kivy_weather_app_package/data.json
kivy_weather_app_package/default.jpg
kivy_weather_app_package/history.json
kivy_weather_app_package/main.py
kivy_weather_app_package/night.jpg
kivy_weather_app_package/rain.jpg
kivy_weather_app_package/snow.jpg
kivy_weather_app_package/sunny.jpg
kivy_weather_app_package/weather.kv
kivy_weather_app_package-1.11.dist-info/LICENSE
kivy_weather_app_package-1.11.dist-info/METADATA
kivy_weather_app_package-1.11.dist-info/WHEEL
kivy_weather_app_package-1.11.dist-info/entry_points.txt
kivy_weather_app_package-1.11.dist-info/top_level.txt
kivy_weather_app_package-1.11.dist-info/RECORD
