Metadata-Version: 2.1
Name: kivy-weather-app-package
Version: 1.11
Summary: UNKNOWN
Home-page: UNKNOWN
Author: Daniel Kříž
License: MIT
Platform: UNKNOWN
License-File: LICENSE
Requires-Dist: kivy
